setup.py
testing12/__init__.py
testing12/secondmax.py
testing12.egg-info/PKG-INFO
testing12.egg-info/SOURCES.txt
testing12.egg-info/dependency_links.txt
testing12.egg-info/top_level.txt